odoo/addons/auth_api_key_group/README.rst
odoo/addons/auth_api_key_group/__init__.py
odoo/addons/auth_api_key_group/__manifest__.py
odoo/addons/auth_api_key_group/i18n/auth_api_key_group.pot
odoo/addons/auth_api_key_group/i18n/it.po
odoo/addons/auth_api_key_group/i18n/zh_CN.po
odoo/addons/auth_api_key_group/models/__init__.py
odoo/addons/auth_api_key_group/models/auth_api_key.py
odoo/addons/auth_api_key_group/models/auth_api_key_group.py
odoo/addons/auth_api_key_group/readme/CONTRIBUTORS.md
odoo/addons/auth_api_key_group/readme/CREDITS.md
odoo/addons/auth_api_key_group/readme/DESCRIPTION.md
odoo/addons/auth_api_key_group/security/ir.model.access.csv
odoo/addons/auth_api_key_group/static/description/icon.png
odoo/addons/auth_api_key_group/static/description/index.html
odoo/addons/auth_api_key_group/tests/__init__.py
odoo/addons/auth_api_key_group/tests/test_auth_api_key_group.py
odoo/addons/auth_api_key_group/views/auth_api_key_group_view.xml
odoo/addons/auth_api_key_group/views/auth_api_key_view.xml
odoo_addon_auth_api_key_group-18.0.1.0.0.4.dist-info/METADATA
odoo_addon_auth_api_key_group-18.0.1.0.0.4.dist-info/WHEEL
odoo_addon_auth_api_key_group-18.0.1.0.0.4.dist-info/top_level.txt
odoo_addon_auth_api_key_group-18.0.1.0.0.4.dist-info/RECORD
