Metadata-Version: 2.1
Name: odoo-addon-auth_api_key_group
Version: 18.0.1.0.0.4
Requires-Python: >=3.10
Requires-Dist: odoo-addon-auth_api_key==18.0.*
Requires-Dist: odoo==18.0.*
Summary: Allow grouping API keys together. Grouping per se does nothing. This feature is supposed to be used by other modules to limit access to services or records based on groups of keys.
Home-page: https://github.com/OCA/server-auth
License: LGPL-3
Author: Camptocamp,Odoo Community Association (OCA)
Author-email: support@odoo-community.org
Classifier: Programming Language :: Python
Classifier: Framework :: Odoo
Classifier: Framework :: Odoo :: 18.0
Classifier: License :: OSI Approved :: GNU Lesser General Public License v3 (LGPLv3)
Classifier: Development Status :: 4 - Beta
